strstyle/__init__.py
strstyle/__main__.py
strstyle/str_style.py
str_style-1.0.1.dist-info/LICENSE
str_style-1.0.1.dist-info/METADATA
str_style-1.0.1.dist-info/WHEEL
str_style-1.0.1.dist-info/entry_points.txt
str_style-1.0.1.dist-info/RECORD
