Metadata-Version: 2.1
Name: str-style
Version: 1.0.1
Summary: str-style is a Python package for enhancing the visual appearance of text. Easily apply a variety of styles like bold, underline, colors, and more to your strings in both CLI and Python scripts.
Home-page: https://github.com/esharf/str-style
License: MIT
Keywords: style,collor
Author: esharf
Author-email: 57587340+esharf@users.noreply.github.com
Requires-Python: >=3.8,<4.0
Classifier: License :: OSI Approved :: MIT License
Classifier: Programming Language :: Python :: 3
Classifier: Programming Language :: Python :: 3.8
Classifier: Programming Language :: Python :: 3.9
Classifier: Programming Language :: Python :: 3.10
Classifier: Programming Language :: Python :: 3.11
Classifier: Programming Language :: Python :: 3.12
Project-URL: Bug Tracker, https://github.com/esharfr/str-style/issues
Project-URL: Repository, https://github.com/esharf/str-style
